{
  "생성_일시": "2025년 1월",
  "버전": "1.0 - 첫 번째 직업군",
  "설명": "매우 유기적이고 독특한 키워드 태그 시스템",
  "키워드_효과_시스템": {
    "균형": {
      "효과": "상황에 따라 공격/방어 모드 자동 전환",
      "조건": "HP 비율과 적 수에 따라 변화",
      "보너스": "모드 전환 시 일시적 능력치 부스트"
    },
    "적응": {
      "효과": "전투 중 적의 패턴에 적응하여 저항/회피 증가",
      "조건": "같은 타입의 공격을 받을수록 저항 증가",
      "보너스": "적응 완료 시 해당 공격 타입에 대한 반격 활성화"
    },
    "전환": {
      "효과": "스킬 사용 후 다른 스킬의 효과가 변화",
      "조건": "직전 사용 스킬에 따라 다음 스킬 강화",
      "보너스": "연계 성공 시 MP 회복 및 쿨다운 감소"
    },
    "마스터": {
      "효과": "모든 무기/방어구 타입에 보너스 적용",
      "조건": "장비 타입에 관계없이 숙련도 보정",
      "보너스": "장비 변경 시에도 능력치 유지"
    },
    "연구": {
      "효과": "스킬 사용할수록 해당 스킬의 효과가 영구 증가",
      "조건": "같은 스킬 반복 사용으로 연구 레벨 상승",
      "보너스": "연구 레벨에 따른 추가 효과 해금"
    },
    "진화": {
      "효과": "전투 중 스킬이 단계별로 진화하여 새로운 효과 획득",
      "조건": "특정 조건 달성 시 스킬 형태 변화",
      "보너스": "진화 단계가 높을수록 MP 효율 증가"
    },
    "지식": {
      "효과": "적의 정보를 분석하여 약점 발견 및 대응책 습득",
      "조건": "같은 적과 전투할수록 정보 축적",
      "보너스": "정보 완성 시 해당 적에게 특효 피해"
    },
    "성장": {
      "효과": "전투 후 경험치로 스킬 자체가 성장하여 능력 향상",
      "조건": "획득 경험치의 일정 비율을 스킬 성장에 투자",
      "보너스": "성장 레벨에 따른 새로운 스킬 변종 해금"
    },
    "기동": {
      "효과": "이동 후 공격 시 피해량과 명중률 대폭 증가",
      "조건": "턴마다 위치 이동 시 기동 스택 축적",
      "보너스": "기동 스택이 높을수록 회피율 증가"
    },
    "회피": {
      "효과": "공격 회피 성공 시 반격 기회 획득",
      "조건": "회피 성공률에 따른 반격 위력 증가",
      "보너스": "연속 회피 시 무적 시간 발생"
    },
    "유격": {
      "효과": "히트앤런 전술로 적을 교란하며 지속 피해",
      "조건": "공격 후 즉시 이동 시 적에게 지속 디버프",
      "보너스": "유격 전술 성공 시 파티 전체 이동력 증가"
    },
    "전술": {
      "효과": "전장 상황을 분석하여 최적의 행동 선택지 제시",
      "조건": "턴 시작 시 현재 상황에 최적화된 스킬 강화",
      "보너스": "전술 활용 시 파티 전체 행동 순서 조정 가능"
    },
    "만능": {
      "효과": "상황에 따라 다양한 유틸리티 효과 발동",
      "조건": "필요에 따라 자동으로 최적 효과 선택",
      "보너스": "만능 스킬 사용 시 다른 스킬 쿨다운 감소"
    },
    "기교": {
      "효과": "정교한 기술로 크리티컬 확률 및 추가 효과 발생",
      "조건": "연속 성공 시 기교 레벨 상승",
      "보너스": "기교 레벨에 따른 특수 효과 해금"
    },
    "효율": {
      "효과": "모든 자원(HP, MP, 아이템) 사용 효율 극대화",
      "조건": "자원 절약 시마다 효율 스택 증가",
      "보너스": "높은 효율 스택 시 모든 행동의 비용 감소"
    },
    "발견": {
      "효과": "숨겨진 요소 발견 및 추가 보상 획득",
      "조건": "탐색 행동 시 발견 확률 증가",
      "보너스": "발견 성공 시 파티 전체에 임시 럭 보너스"
    }
  },
  "강화된_스킬들": {
    "전사": {
      "직업_설계": {
        "설계_이름": "⚡ 균형의 전투마스터",
        "컨셉": "공수균형과 상황적응의 올라운더",
        "특징": [
          "상황별 전환",
          "적응형 스탯",
          "다목적 스킬"
        ],
        "키워드": [
          "균형",
          "적응",
          "전환",
          "마스터"
        ],
        "핵심특성": [
          "불굴의_의지",
          "방어_숙련",
          "전투_광기"
        ],
        "선택_번호": 3
      },
      "스킬_강화": {
        "방패_강타": {
          "원래_설명": "방패로 강력한 타격을 가합니다.",
          "키워드_태그": "[균형][적응]",
          "새로운_설명": "[균형][적응] 방패강타 - 상황에 맞춰 공격과 방어를 겸비한 균형잡힌 타격",
          "유기적_효과": {
            "기본_효과": "공격력의 120% 물리 피해",
            "균형_효과": "HP 50% 이상: +30% 피해, HP 50% 이하: +30% 방어력",
            "적응_효과": "받은 피해 타입에 따라 다음 방패강타가 해당 타입 저항 +25%",
            "시너지": "적응 3회 누적 시 완벽한 반격으로 변화 (피해 무효 + 2배 반격)"
          }
        },
        "파괴의_일격": {
          "원래_설명": "모든 힘을 모아 파괴적인 일격을 날립니다.",
          "키워드_태그": "[전환][마스터]",
          "새로운_설명": "[전환][마스터] 파괴의일격 - 직전 행동을 분석하여 최적화된 파괴적 타격",
          "유기적_효과": {
            "기본_효과": "공격력의 200% 물리 피해",
            "전환_효과": "직전 스킬이 방어형이면 +50% 피해, 공격형이면 +30% 크리티컬",
            "마스터_효과": "장비 타입에 관계없이 최대 숙련도 보정 적용",
            "시너지": "전환 성공 시 다음 턴 모든 스킬 MP 소모량 50% 감소"
          }
        }
      }
    },
    "아크메이지": {
      "직업_설계": {
        "설계_이름": "📚 현자의 연구자",
        "컨셉": "지식과 연구로 성장하는 학자형 마법사",
        "특징": [
          "경험치 보너스",
          "스킬 진화",
          "지식 축적"
        ],
        "키워드": [
          "연구",
          "진화",
          "지식",
          "성장"
        ],
        "핵심특성": [
          "마법_연구자",
          "마나_순환",
          "원소_지배"
        ],
        "선택_번호": 3
      },
      "스킬_강화": {
        "마력_파동": {
          "원래_설명": "마력의 순수한 파동으로 적을 공격합니다.",
          "키워드_태그": "[연구][성장]",
          "새로운_설명": "[연구][성장] 마력파동 - 사용할수록 진화하는 순수 마력의 결정체",
          "유기적_효과": {
            "기본_효과": "마법공격력의 110% 무속성 마법 피해",
            "연구_효과": "사용 횟수 × 5% 추가 피해 (최대 100%)",
            "성장_효과": "획득 경험치 100당 영구적으로 기본 피해 +1% (최대 50%)",
            "시너지": "연구 레벨 10 달성 시 '마력 폭발'로 진화 (광역 피해)"
          }
        },
        "마력_폭발": {
          "원래_설명": "폭발하는 마력으로 광역 피해를 입힙니다.",
          "키워드_태그": "[진화][지식]",
          "새로운_설명": "[진화][지식] 마력폭발 - 축적된 지식을 바탕으로 진화한 고위 마법",
          "유기적_효과": {
            "기본_효과": "마법공격력의 140% 광역 무속성 피해",
            "진화_효과": "전투 중 3단계까지 진화 (1단계: +20%, 2단계: +40%, 3단계: +80%)",
            "지식_효과": "분석한 적의 수 × 10% 추가 피해",
            "시너지": "3단계 진화 + 지식 5개 이상 시 '현자의 심판'으로 최종 진화"
          }
        }
      }
    },
    "궁수": {
      "직업_설계": {
        "설계_이름": "💨 기동형 유격수",
        "컨셉": "빠른 이동과 회피로 살아남는 전술가",
        "특징": [
          "이동 보너스",
          "회피 특화",
          "히트앤런"
        ],
        "키워드": [
          "기동",
          "회피",
          "유격",
          "전술"
        ],
        "핵심특성": [
          "민첩한_몸놀림",
          "바람의_가호",
          "원거리_숙련"
        ],
        "선택_번호": 2
      },
      "스킬_강화": {
        "삼연사": {
          "원래_설명": "세 발의 화살을 연속으로 발사합니다.",
          "키워드_태그": "[기동][유격]",
          "새로운_설명": "[기동][유격] 삼연사 - 기동성을 활용한 유격전 전용 연사 기법",
          "유기적_효과": {
            "기본_효과": "물리공격력의 70% × 3회 공격",
            "기동_효과": "이동 거리에 비례하여 각 화살 +5~25% 피해",
            "유격_효과": "공격 후 자동으로 안전한 위치로 이동, 적에게 '혼란' 디버프",
            "시너지": "기동 스택 5개 + 유격 성공 시 '바람의 화살비'로 변화 (5연사)"
          }
        },
        "관통사격": {
          "원래_설명": "적을 관통하는 강력한 화살을 발사합니다.",
          "키워드_태그": "[회피][전술]",
          "새로운_설명": "[회피][전술] 관통사격 - 전술적 위치 선정과 회피 기동을 겸비한 정밀 사격",
          "유기적_효과": {
            "기본_효과": "물리공격력의 180% 관통 피해",
            "회피_효과": "발사 후 일정 시간 회피율 +50%, 회피 성공 시 재사용 쿨다운 초기화",
            "전술_효과": "전장 분석으로 최적 각도 계산, 관통된 적 수만큼 다음 공격 +20%",
            "시너지": "회피 3회 + 전술 분석 완료 시 '신속의 일격'으로 진화"
          }
        }
      }
    },
    "도적": {
      "직업_설계": {
        "설계_이름": "🤏 만능 도적",
        "컨셉": "아이템과 기교로 승부하는 만능 서포터",
        "특징": [
          "아이템 효율",
          "보물 발견",
          "유틸리티"
        ],
        "키워드": [
          "만능",
          "기교",
          "효율",
          "발견"
        ],
        "핵심특성": [
          "빠른_손놀림",
          "도적의_직감",
          "그림자_은신"
        ],
        "선택_번호": 3
      },
      "스킬_강화": {
        "독침": {
          "원래_설명": "독이 발린 침을 던집니다.",
          "키워드_태그": "[만능][기교]",
          "새로운_설명": "[만능][기교] 독침 - 상황에 맞는 최적의 독을 정교하게 조합한 만능 도구",
          "유기적_효과": {
            "기본_효과": "물리공격력의 80% 피해 + 독 상태이상",
            "만능_효과": "적의 상태에 따라 독 타입 자동 변경 (출혈독, 마비독, 환각독 등)",
            "기교_효과": "정확한 급소 조준으로 크리티컬 확률 +30%, 성공 시 독 지속시간 2배",
            "시너지": "기교 레벨 5 + 만능 독 5종 이상 사용 시 '만독의 달인' 상태 획득"
          }
        },
        "암살": {
          "원래_설명": "은밀하게 적의 급소를 노립니다.",
          "키워드_태그": "[효율][발견]",
          "새로운_설명": "[효율][발견] 암살 - 효율적인 정보 수집을 통해 발견한 완벽한 급소 공격",
          "유기적_효과": {
            "기본_효과": "물리공격력의 250% 치명타 피해",
            "효율_효과": "MP 소모량 50% 감소, 성공 시 다음 2턴간 모든 스킬 비용 -30%",
            "발견_효과": "적의 숨겨진 약점 발견으로 방어력 무시 + 특수 상태이상 부여",
            "시너지": "효율 극대화 + 발견 정보 축적 시 '완벽한 암살' 모드 진입"
          }
        }
      }
    }
  },
  "구현_지침": {
    "키워드_표시": "스킬 설명 맨 앞에 [키워드] 형태로 표시",
    "효과_적용": "키워드별 유기적 효과가 실시간으로 적용",
    "시너지_시스템": "여러 키워드 조합 시 특별한 시너지 효과 발동",
    "성장_시스템": "사용할수록 키워드 효과가 성장하고 진화"
  }
}